selenium_testing_library/__init__.py
selenium_testing_library/locators.py
selenium_testing_library/main.js
selenium_testing_library/py.typed
selenium_testing_library/screen.py
selenium_testing_library-2024.3.dist-info/LICENSE.md
selenium_testing_library-2024.3.dist-info/METADATA
selenium_testing_library-2024.3.dist-info/WHEEL
selenium_testing_library-2024.3.dist-info/RECORD
