Metadata-Version: 2.1
Name: selenium-testing-library
Version: 2024.3
Summary: A Python Selenium library inspired by the Testing Library
Home-page: https://github.com/anze3db/selenium-testing-library
License: MIT
Author: Anže Pečar
Author-email: anze@pecar.me
Requires-Python: >=3.8,<4.0
Classifier: License :: OSI Approved :: MIT License
Classifier: Programming Language :: Python :: 3
Classifier: Programming Language :: Python :: 3.8
Classifier: Programming Language :: Python :: 3.9
Classifier: Programming Language :: Python :: 3.10
Classifier: Programming Language :: Python :: 3.11
Classifier: Programming Language :: Python :: 3.12
Requires-Dist: selenium (>3.0.0)
Project-URL: Changelog, https://github.com/anze3db/selenium-testing-library/blob/main/CHANGELOG.md
Project-URL: Repository, https://github.com/anze3db/selenium-testing-library
